setup.cfg
setup.py
scim.egg-info/PKG-INFO
scim.egg-info/SOURCES.txt
scim.egg-info/dependency_links.txt
scim.egg-info/requires.txt
scim.egg-info/top_level.txt
src/scim/__init__.py
src/scim/schema/__init__.py
src/scim/schema/attributes.py
src/scim/schema/core.py
src/scim/schema/tenant.py
src/scim/schema/types.py
src/scim/schema/user.py