Metadata-Version: 1.1
Name: scim
Version: 0.1.0
Summary: A python interface to produce and consume System for Cross-domain Identity Management (SCIM) messages.
Home-page: http://github.com/concordusapps/python-scim
Author: Concordus Applications
Author-email: support@concordusapps.com
License: UNKNOWN
Platform: UNKNOWN
Classifier: Development Status :: 3 - Alpha
Classifier: Intended Audience :: Developers
Classifier: Intended Audience :: System Administrators
Classifier: License :: OSI Approved :: MIT License
Classifier: Operating System :: OS Independent
Classifier: Programming Language :: Python :: 3.3
